media_management_scripts/__init__.py
media_management_scripts/convert.py
media_management_scripts/convert_daemon.py
media_management_scripts/main.py
media_management_scripts/moviedb.py
media_management_scripts/renamer.py
media_management_scripts/tvdb_api.py
media_management_scripts/utils.py
media_management_scripts/commands/__init__.py
media_management_scripts/commands/combine_subtitles.py
media_management_scripts/commands/common.py
media_management_scripts/commands/compare_directories.py
media_management_scripts/commands/concat_mp4.py
media_management_scripts/commands/convert.py
media_management_scripts/commands/create_test_video.py
media_management_scripts/commands/executables.py
media_management_scripts/commands/filebot.py
media_management_scripts/commands/find_episodes.py
media_management_scripts/commands/itunes.py
media_management_scripts/commands/map_rename.py
media_management_scripts/commands/metadata.py
media_management_scripts/commands/metadata_compare.py
media_management_scripts/commands/movie_rename.py
media_management_scripts/commands/rename.py
media_management_scripts/commands/search.py
media_management_scripts/commands/select_streams.py
media_management_scripts/commands/split.py
media_management_scripts/commands/subtitles.py
media_management_scripts/commands/thumbnail.py
media_management_scripts/commands/tv_rename.py
media_management_scripts/support/__init__.py
media_management_scripts/support/combine_all.py
media_management_scripts/support/concat_mp4.py
media_management_scripts/support/encoding.py
media_management_scripts/support/episode_finder.py
media_management_scripts/support/executables.py
media_management_scripts/support/files.py
media_management_scripts/support/formatting.py
media_management_scripts/support/interlace.py
media_management_scripts/support/metadata.py
media_management_scripts/support/movie_rename.py
media_management_scripts/support/search_parser.py
media_management_scripts/support/split.py
media_management_scripts-0.5.3.dist-info/LICENSE
media_management_scripts-0.5.3.dist-info/METADATA
media_management_scripts-0.5.3.dist-info/WHEEL
media_management_scripts-0.5.3.dist-info/entry_points.txt
media_management_scripts-0.5.3.dist-info/top_level.txt
media_management_scripts-0.5.3.dist-info/RECORD
