Metadata-Version: 2.1
Name: media-management-scripts
Version: 0.5.3
Summary: Media Management Scripts
Author: Ray Douglass
License: Apache 2.0
Project-URL: Homepage, https://github.com/raydouglass/media_management_scripts
Classifier: License :: OSI Approved :: Apache Software License
Classifier: Programming Language :: Python
Classifier: Programming Language :: Python :: 3
Requires-Python: >=3.9
License-File: LICENSE
Requires-Dist: pycaption
Requires-Dist: pyparsing
Requires-Dist: python-magic
Requires-Dist: pythondialog
Requires-Dist: pyyaml
Requires-Dist: requests
Requires-Dist: tempita
Requires-Dist: texttable
Requires-Dist: tmdbsimple
